VirtualAssitant/__init__.py
VirtualAssitant/assistent.py
VirtualAssitant/calendar_setup.py
VirtualAssitant/credentials.json
virtualassitant-1.1.2.dist-info/entry_points.txt
virtualassitant-1.1.2.dist-info/WHEEL
virtualassitant-1.1.2.dist-info/METADATA
virtualassitant-1.1.2.dist-info/RECORD
