Metadata-Version: 2.1
Name: virtualassitant
Version: 1.1.2
Summary: Agendamiento de actividades mediante comandos de voz en google calendar
License: MIT
Keywords: google,calendar
Author: Danilo
Author-email: drleon416@gmail.com
Requires-Python: >=3.8,<4.0
Classifier: License :: OSI Approved :: MIT License
Classifier: Programming Language :: Python :: 3
Classifier: Programming Language :: Python :: 3.10
Classifier: Programming Language :: Python :: 3.8
Classifier: Programming Language :: Python :: 3.9
Requires-Dist: click (>=8.1.3,<9.0.0)
